.editorconfig
.gitignore
.nojekyll
AUTHORS.rst
CONTRIBUTING.rst
HISTORY.rst
LICENSE
MANIFEST.in
Makefile
README.rst
index.html
requirements_dev.txt
setup.cfg
setup.py
tox.ini
.github/ISSUE_TEMPLATE.md
docs/Makefile
docs/authors.rst
docs/conf.py
docs/contributing.rst
docs/history.rst
docs/index.rst
docs/installation.rst
docs/make.bat
docs/readme.rst
docs/usage.rst
docs/_build/singlehtml/index.html
docs/_build/singlehtml/_static/ajax-loader.gif
docs/_build/singlehtml/_static/alabaster.css
docs/_build/singlehtml/_static/basic.css
docs/_build/singlehtml/_static/comment-bright.png
docs/_build/singlehtml/_static/comment-close.png
docs/_build/singlehtml/_static/comment.png
docs/_build/singlehtml/_static/custom.css
docs/_build/singlehtml/_static/doctools.js
docs/_build/singlehtml/_static/documentation_options.js
docs/_build/singlehtml/_static/down-pressed.png
docs/_build/singlehtml/_static/down.png
docs/_build/singlehtml/_static/file.png
docs/_build/singlehtml/_static/jquery-3.2.1.js
docs/_build/singlehtml/_static/jquery.js
docs/_build/singlehtml/_static/language_data.js
docs/_build/singlehtml/_static/minus.png
docs/_build/singlehtml/_static/plus.png
docs/_build/singlehtml/_static/pygments.css
docs/_build/singlehtml/_static/searchtools.js
docs/_build/singlehtml/_static/underscore-1.3.1.js
docs/_build/singlehtml/_static/underscore.js
docs/_build/singlehtml/_static/up-pressed.png
docs/_build/singlehtml/_static/up.png
docs/_build/singlehtml/_static/websupport.js
kinjector/__init__.py
kinjector/cli.py
kinjector/kinjector.py
kinjector/pckg_info.py
kinjector.egg-info/PKG-INFO
kinjector.egg-info/SOURCES.txt
kinjector.egg-info/dependency_links.txt
kinjector.egg-info/entry_points.txt
kinjector.egg-info/not-zip-safe
kinjector.egg-info/requires.txt
kinjector.egg-info/top_level.txt
tests/__init__.py
tests/brd_test_in.json
tests/brd_test_in.yaml
tests/brd_test_out.json
tests/brd_test_out.yaml
tests/dr_test_in.json
tests/dr_test_in.yaml
tests/dr_test_out.json
tests/dr_test_out.yaml
tests/fp-info-cache
tests/nca_test_in.json
tests/nca_test_in.yaml
tests/nca_test_out.json
tests/nca_test_out.yaml
tests/ncd_test_in.json
tests/ncd_test_in.yaml
tests/ncd_test_out.json
tests/ncd_test_out.yaml
tests/setup_teardown.py
