Metadata-Version: 2.1
Name: kinjector
Version: 1.0.0
Summary: Inject/eject JSON/YAML data to/from KiCad files.
Home-page: https://github.com/devbisme/kinjector
Author: Dave Vandenbout
Author-email: devb@xess.com
License: MIT license
Project-URL: Documentation, https://devbisme.github.io/kinjector
Project-URL: Source, https://github.com/devbisme/kinjector
Project-URL: Changelog, https://github.com/devbisme/kinjector/blob/master/HISTORY.rst
Project-URL: Tracker, https://github.com/devbisme/kinjector/issues
Keywords: kinjector
Platform: UNKNOWN
Classifier: Development Status :: 5 - Production/Stable
Classifier: Intended Audience :: Manufacturing
Classifier: License :: OSI Approved :: MIT License
Classifier: Natural Language :: English
Classifier: Operating System :: OS Independent
Classifier: Programming Language :: Python :: 2.7
Classifier: Programming Language :: Python :: 3
Classifier: Topic :: Scientific/Engineering :: Electronic Design Automation (EDA)
License-File: LICENSE
License-File: AUTHORS.rst
